[
  {
    "repo": "avsm/melange",
    "tags": [
      "fromMirageBot"
    ]
  },
  {
    "repo": "mor1/ocaml-mrt",
    "tags": [
      "fromMirageBot"
    ]
  },
  {
    "repo": "avsm/ezxmlm",
    "tags": [
      "fromMirageBot"
    ]
  },
  {
    "repo": "avsm/vagrant-opam",
    "tags": [
      "fromMirageBot"
    ]
  },
  {
    "repo": "avsm/opam-sync-github-prs",
    "tags": [
      "fromMirageBot"
    ]
  },
  {
    "repo": "mirleft/ocaml-asn1-combinators",
    "tags": [
      "fromMirageBot"
    ]
  },
  {
    "repo": "mirleft/ocaml-tls",
    "tags": [
      "fromMirageBot"
    ]
  },
  {
    "repo": "mirleft/ocaml-nocrypto",
    "tags": [
      "fromMirageBot"
    ]
  },
  {
    "repo": "mirleft/tls-demo-server",
    "tags": [
      "fromMirageBot"
    ]
  },
  {
    "repo": "mirleft/ocaml-x509",
    "tags": [
      "fromMirageBot"
    ]
  },
  {
    "repo": "hannesm/jackline",
    "tags": [
      "fromMirageBot"
    ]
  },
  {
    "repo": "avsm/ocaml-dockerfile",
    "tags": [
      "fromMirageBot"
    ]
  },
  {
    "repo": "avsm/ocaml-docker-scripts",
    "tags": [
      "fromMirageBot"
    ]
  },
  {
    "repo": "mirleft/btc-pinata",
    "tags": [
      "fromMirageBot"
    ]
  },
  {
    "repo": "samoht/ocaml-huffman-code",
    "tags": [
      "fromMirageBot"
    ]
  },
  {
    "repo": "samoht/ocaml-lz77",
    "tags": [
      "fromMirageBot"
    ]
  },
  {
    "repo": "hannesm/tlstunnel",
    "tags": [
      "fromMirageBot"
    ]
  },
  {
    "repo": "hannesm/tlsclient",
    "tags": [
      "fromMirageBot"
    ]
  },
  {
    "repo": "mirleft/nqsb.io",
    "tags": [
      "fromMirageBot"
    ]
  },
  {
    "repo": "mor1/ocaml-tftp",
    "tags": [
      "fromMirageBot"
    ]
  },
  {
    "repo": "pqwy/notty",
    "tags": [
      "fromMirageBot"
    ]
  },
  {
    "repo": "pqwy/ocaml-signalfd",
    "tags": [
      "fromMirageBot"
    ]
  },
  {
    "repo": "pqwy/ocaml-pctrl",
    "tags": [
      "fromMirageBot"
    ]
  },
  {
    "repo": "mirleft/tlstools",
    "tags": [
      "fromMirageBot"
    ]
  },
  {
    "repo": "avsm/opam-solver-proxy",
    "tags": [
      "fromMirageBot"
    ]
  },
  {
    "repo": "avsm/ocaml-docker-infra",
    "tags": [
      "fromMirageBot"
    ]
  },
  {
    "repo": "pqwy/ocaml-sendmsg",
    "tags": [
      "fromMirageBot"
    ]
  },
  {
    "repo": "isakmp/ike",
    "tags": [
      "fromMirageBot"
    ]
  },
  {
    "repo": "hannesm/telnet",
    "tags": [
      "fromMirageBot"
    ]
  },
  {
    "repo": "avsm/dopam",
    "tags": [
      "fromMirageBot"
    ]
  }
]
